weibo_trending/__init__.py
weibo_trending/__main__.py
weibo_trending-0.0.6.dist-info/METADATA
weibo_trending-0.0.6.dist-info/WHEEL
weibo_trending-0.0.6.dist-info/licenses/LICENSE
weibo_trending-0.0.6.dist-info/RECORD
