Metadata-Version: 2.1
Name: weibo_trending
Version: 0.0.6
Summary: Weibo trending posts scraper
Project-URL: Homepage, https://github.com/ericlingit/weibo-trending
Project-URL: Bug Tracker, https://github.com/ericlingit/weibo-trending/issues
Author-email: Eric Lin <ericlingit@users.noreply.github.com>
License-File: LICENSE
Classifier: License :: OSI Approved :: GNU General Public License v3 (GPLv3)
Classifier: Operating System :: OS Independent
Classifier: Programming Language :: Python :: 3
Classifier: Topic :: Utilities
Requires-Python: >=3.7
Requires-Dist: beautifulsoup4
Requires-Dist: brotli
Requires-Dist: lxml
Requires-Dist: requests
